{"name":"Maël Nison","company":"Yarn","title":"Lead Maintainer","image":{"url":"mael-nison.jpeg"},"bio":"Maël has worked with code repositories from small open source projects to large corporate behemoths. These experiences led to the development of many features seen in Yarn, the JavaScript package manager. Today, Maël is a Senior Software Engineer at Datadog, where he works on developer experience and continues to maintain Yarn.","twitter":"arcanis","linkedin":"","github":"arcanis","abstract":"\n\t\t<div>\n\t\t  <p>\n\t\t\t<strong>Monorepos, are they right for you?</strong>\n\t\t  </p>\n\t\t  <p>\n\t\t\tMonorepos are back and more popular than ever. In this talk, we’ll dive into the problems\n\t\t\tthey solve, the challenges they create, and how they stack up to the alternatives. By the\n\t\t\tend of this presentation, you’ll have a better idea why so many communities find them\n\t\t\tappealing, and how to decide if monorepos are a good fit for your current and future\n\t\t\tprojects.\n\t\t  </p>\n\t\t</div>\n\t  "}